setup.py
evalout/__init__.py
evalout.egg-info/PKG-INFO
evalout.egg-info/SOURCES.txt
evalout.egg-info/dependency_links.txt
evalout.egg-info/not-zip-safe
evalout.egg-info/top_level.txt
evalout/image_classification/__init__.py
evalout/image_classification/calculate.py
evalout/image_classification/evalout.py
evalout/object_detection/__init__.py
evalout/object_detection/calculate.py
evalout/object_detection/evalout.py
evalout/semantic_segmentation/__init__.py
evalout/semantic_segmentation/calculate.py
evalout/semantic_segmentation/evalout.py