Metadata-Version: 2.1
Name: evalout
Version: 0.0.2
Summary: evalout
Home-page: https://gitee.com/AlwaysLee/cgf-ml_sdk-python.git
Author: cgf
Author-email: 512070806@qq.com
License: MIT
Platform: UNKNOWN
